<?xml version="1.0" encoding="utf-8" ?>
<ThingDefs>

  <ThingDef Name="MealBase" Abstract="True">
    <thingClass>ThingWithComps</thingClass>
    <category>Item</category>
    <useHitPoints>true</useHitPoints>
    <selectable>true</selectable>
    <statBases>
      <MaxHitPoints>50</MaxHitPoints>
      <Flammability>1.0</Flammability>
			<Beauty>-4</Beauty>
			<Mass>0.44</Mass>
			<DeteriorationRate>10</DeteriorationRate>
		</statBases>
    <altitudeLayer>Item</altitudeLayer>
    <stackLimit>10</stackLimit>
    <tickerType>Rare</tickerType>
    <socialPropernessMatters>true</socialPropernessMatters>
    <thingCategories>
      <li>FoodMeals</li>
    </thingCategories>
    <alwaysHaulable>true</alwaysHaulable>
    <comps>
      <li Class="CompProperties_Forbiddable" />
      <li Class="CompProperties_Ingredients" />
      <li Class="CompProperties_FoodPoisonable" />
    </comps>
    <pathCost>15</pathCost>
    <resourceReadoutPriority>Last</resourceReadoutPriority>
    <drawGUIOverlay>true</drawGUIOverlay>
    <ingestible>
      <foodType>Meal</foodType>
      <maxNumToIngestAtOnce>1</maxNumToIngestAtOnce>
      <optimalityOffset>16</optimalityOffset>
    </ingestible>
  </ThingDef>


  <ThingDef ParentName="MealBase">
    <defName>MealSurvivalPack</defName>
    <label>Twinkie</label>
    <description>A Twinkie is an American snack cake, marketed as a "Golden Sponge Cake with Creamy Filling."</description>
    <graphicData>
      <texPath>Twinkie</texPath>
      <graphicClass>Graphic_Single</graphicClass>
    </graphicData>
    <statBases>
      <DeteriorationRate>0.5</DeteriorationRate>
      <MarketValue>25</MarketValue>
      <Mass>0.4</Mass>
      <WorkToMake>1400</WorkToMake>
    </statBases>
    <ingestible>
      <preferability>MealSimple</preferability>
			<nutrition>0.90</nutrition>
			<optimalityOffset>-5</optimalityOffset>
			<ingestEffect>EatVegetarian</ingestEffect>
      <ingestSound>Meal_Eat</ingestSound>
    </ingestible>
  </ThingDef>

</ThingDefs>